setup.py
drf_spectacular/__init__.py
drf_spectacular/authentication.py
drf_spectacular/drainage.py
drf_spectacular/extensions.py
drf_spectacular/generators.py
drf_spectacular/helpers.py
drf_spectacular/hooks.py
drf_spectacular/openapi.py
drf_spectacular/plumbing.py
drf_spectacular/renderers.py
drf_spectacular/serializers.py
drf_spectacular/settings.py
drf_spectacular/types.py
drf_spectacular/utils.py
drf_spectacular/views.py
drf_spectacular/contrib/__init__.py
drf_spectacular/contrib/django_filters.py
drf_spectacular/contrib/django_oauth_toolkit.py
drf_spectacular/contrib/djangorestframework_camel_case.py
drf_spectacular/contrib/rest_auth.py
drf_spectacular/contrib/rest_framework_jwt.py
drf_spectacular/contrib/rest_framework_simplejwt.py
drf_spectacular/contrib/rest_polymorphic.py
drf_spectacular/management/__init__.py
drf_spectacular/management/commands/__init__.py
drf_spectacular/management/commands/spectacular.py
drf_spectacular/validation/__init__.py
expanded_drf_spectacular.egg-info/PKG-INFO
expanded_drf_spectacular.egg-info/SOURCES.txt
expanded_drf_spectacular.egg-info/dependency_links.txt
expanded_drf_spectacular.egg-info/requires.txt
expanded_drf_spectacular.egg-info/top_level.txt